<?xml version="1.0" encoding="UTF-8"?>
<beans xmlns="http://www.springframework.org/schema/beans"
       xmlns:xsi="http://www.w3.org/2001/XMLSchema-instance"
       xsi:schemaLocation="http://www.springframework.org/schema/beans http://www.springframework.org/schema/beans/spring-beans.xsd">
<bean id="orders" class="Spring01.Bean生命周期.Orders" init-method="initMethod" destroy-method="destoryMethod">
    <property name="oname" value="mobilephone"></property>
</bean>
    <bean id="book" class="Spring01.把list提取出来.Book"></bean>
<!--    配置后置处理器 会为每一个bean实例对象配置后置处理器并且实现里面的2个方法-->
<bean id="myBeanPost" class="Spring01.Bean生命周期.MyBeanPost" ></bean>
</beans>
